main.py
gigachain_core-100.0.4.dist-info/METADATA
gigachain_core-100.0.4.dist-info/WHEEL
gigachain_core-100.0.4.dist-info/top_level.txt
gigachain_core-100.0.4.dist-info/RECORD
