Metadata-Version: 2.4
Name: gigachain-core
Version: 100.0.4
Summary: ⚠️⚠️⚠️ This package was deprectaed. Upgrade to clear langchain + langchain_gigachat. Uninstall all gigachain-* packages! ⚠️⚠️⚠️
Requires-Python: >=3.12
